malloovia/__init__.py
malloovia/__version__.py
malloovia/cli.py
malloovia/lpsolver.py
malloovia/malloovia.schema.yaml
malloovia/model.py
malloovia/phases.py
malloovia/problem.schema.yaml
malloovia/py.test
malloovia/py.typed
malloovia/solution_model.py
malloovia/util.py
malloovia-2.3.2.dist-info/LICENSE
malloovia-2.3.2.dist-info/WHEEL
malloovia-2.3.2.dist-info/METADATA
malloovia-2.3.2.dist-info/RECORD
