Metadata-Version: 2.1
Name: malloovia
Version: 2.3.2
Summary: Use linear programming to allocate applications to cloud infrastructure
License: MIT
Author: Jose Luis Diaz
Author-email: jldiaz@uniovi.es
Requires-Python: >=3.7,<4.0
Classifier: License :: OSI Approved :: MIT License
Classifier: Programming Language :: Python :: 3
Classifier: Programming Language :: Python :: 3.7
Classifier: Programming Language :: Python :: 3.8
Classifier: Programming Language :: Python :: 3.9
Classifier: Programming Language :: Python :: 3.10
Classifier: Programming Language :: Python :: 3.11
Requires-Dist: click (>=8.1.3,<9.0.0)
Requires-Dist: jsonschema (>=4.17.3,<5.0.0)
Requires-Dist: progress (>=1.6,<2.0)
Requires-Dist: pulp (==2.0)
Requires-Dist: ruamel.yaml (>=0.17.21,<0.18.0)
